evolutionary_grid
